{
  "hash": "8ef0783f1fc08cb087bdbd2c77cacc04d8865bf2e3f988bb8c113ea19734b7e0",
  "readable_name": "10.20.1.105_disk_space_lstm-attention_lb60_h128_l2_hor2000",
  "fingerprint": {
    "aggregation_method": "weighted",
    "aggregation_weight_tau": 1.0,
    "batch_size": 128,
    "bias_correction": true,
    "context": "ip.tcppackets",
    "csv_file": "10.20.1.105_disk_space.csv",
    "dimension": "received",
    "dropout": 0.2,
    "epochs": 150,
    "hidden_size": 128,
    "horizon": 2000,
    "ip": "localhost",
    "learning_rate": 0.001,
    "lookback": 60,
    "model": "lstm-attention",
    "num_layers": 2,
    "prediction_smoothing": 1,
    "scaler_type": "none",
    "train_window": 2090,
    "use_differencing": true,
    "window": 90
  }
}